{
	"hp": 20,
	"attack": 30,
	"body_attack": 24,
	"defense": 0,
	"speed": 50.0,
	"exp": 50,
	"coin": 40,
	"invulnerable_time": 0.2,
	"bounding_box": [-25.0, 0.0, 25.0, 68.0],
	"item": {
		"large health potion": 0.1,
		"small attack potion": 0.05,
		"small defense potion": 0.05,
		"panacea": 0.01
	},
	"skills": [
		{
			"mob_animation": "fire_imp_attack",
			"aoe_prototype": "fire_imp_attack_fire",
			"cooldown": 3.0,
			"attach_to_entity": false
		}
	],
	"ai": {
		"type": 2
	},
	"is_boss": false
}
